amazontrends/__init__.py
amazontrends/amazontrends.py
amazontrends/category.py
amazontrends-0.0.6.dist-info/METADATA
amazontrends-0.0.6.dist-info/WHEEL
amazontrends-0.0.6.dist-info/top_level.txt
amazontrends-0.0.6.dist-info/RECORD
