Metadata-Version: 2.1
Name: amazontrends
Version: 0.0.6
Summary: amazontrends
Home-page: https://github.com/kkristof200/AmazonTrends
Author: Kristof
License: UNKNOWN
Platform: UNKNOWN
Classifier: Programming Language :: Python :: 3
Classifier: License :: OSI Approved :: MIT License
Classifier: Operating System :: OS Independent
Requires-Python: >=3.5
Requires-Dist: kcu
